{
    "type": "Collection",
    "id": "modis-64A1-061",
    "stac_version": "1.0.0",
    "description": "{{ collection.description }}",
    "links": [
        {
            "rel": "help",
            "href": "https://lpdaac.usgs.gov/documents/1006/MCD64_User_Guide_V61.pdf",
            "title": "MCD64 User Guide"
        },
        {
            "rel": "describedby",
            "href": "https://ladsweb.modaps.eosdis.nasa.gov/filespec/MODIS/61/MCD64A1",
            "title": "MCD64A1 file specification"
        },
        {
            "rel": "cite-as",
            "href": "https://doi.org/10.5067/MODIS/MCD64A1.061",
            "title": "LP DAAC - MCD64A1"
        },
        {
            "rel": "license",
            "href": "https://lpdaac.usgs.gov/data/data-citation-and-policies/",
            "title": "LP DAAC - Data Citation and Policies"
        },
        {
            "rel": "describedby",
            "href": "https://planetarycomputer.microsoft.com/dataset/modis-64A1-061",
            "type": "text/html",
            "title": "Human readable dataset overview and reference"
        }
    ],
    "stac_extensions": [
        "https://stac-extensions.github.io/raster/v1.0.0/schema.json",
        "https://stac-extensions.github.io/item-assets/v1.0.0/schema.json",
        "https://stac-extensions.github.io/scientific/v1.0.0/schema.json",
        "https://stac-extensions.github.io/table/v1.2.0/schema.json"
    ],
    "item_assets": {
        "QA": {
            "type": "image/tiff; application=geotiff; profile=cloud-optimized",
            "roles": [
                "data"
            ],
            "title": "Quality Assurance Indicators",
            "raster:bands": [
                {
                    "data_type": "uint8",
                    "spatial_resolution": 500
                }
            ]
        },
        "hdf": {
            "type": "application/x-hdf",
            "roles": [
                "data"
            ],
            "title": "Source data containing all bands"
        },
        "Last_Day": {
            "type": "image/tiff; application=geotiff; profile=cloud-optimized",
            "roles": [
                "data"
            ],
            "title": "Last day of the year of reliable change detection",
            "raster:bands": [
                {
                    "unit": "Day",
                    "data_type": "int16",
                    "spatial_resolution": 500
                }
            ]
        },
        "metadata": {
            "type": "application/xml",
            "roles": [
                "metadata"
            ],
            "title": "Federal Geographic Data Committee (FGDC) Metadata"
        },
        "Burn_Date": {
            "type": "image/tiff; application=geotiff; profile=cloud-optimized",
            "roles": [
                "data"
            ],
            "title": "Burn day of year",
            "raster:bands": [
                {
                    "unit": "Day",
                    "data_type": "int16",
                    "spatial_resolution": 500
                }
            ]
        },
        "First_Day": {
            "type": "image/tiff; application=geotiff; profile=cloud-optimized",
            "roles": [
                "data"
            ],
            "title": "First day of the year of reliable change detection",
            "raster:bands": [
                {
                    "unit": "Day",
                    "data_type": "int16",
                    "spatial_resolution": 500
                }
            ]
        },
        "Burn_Date_Uncertainty": {
            "type": "image/tiff; application=geotiff; profile=cloud-optimized",
            "roles": [
                "data"
            ],
            "title": "Estimated uncertainty in burn day",
            "raster:bands": [
                {
                    "unit": "Day",
                    "data_type": "uint8",
                    "spatial_resolution": 500
                }
            ]
        }
    },
    "msft:group_id": "modis",
    "msft:container": "modis-061",
    "sci:publications": [
        {
            "doi": "10.5067/MODIS/MCD64A1.061",
            "citation": "Giglio, L., Justice, C., Boschetti, L., &amp; Roy, D. (2021). <i>MODIS/Terra+Aqua Burned Area Monthly L3 Global 500m SIN Grid V061</i> [Data set]. NASA EOSDIS Land Processes DAAC. https://doi.org/10.5067/MODIS/MCD64A1.061"
        }
    ],
    "msft:storage_account": "modiseuwest",
    "msft:short_description": "MODIS Burned Area Monthly",
    "msft:region": "westeurope",
    "title": "MODIS Burned Area Monthly",
    "extent": {
        "spatial": {
            "bbox": [
                [
                    -180,
                    -90,
                    180,
                    90
                ]
            ]
        },
        "temporal": {
            "interval": [
                [
                    "2000-11-01T00:00:00Z",
                    null
                ]
            ]
        }
    },
    "license": "proprietary",
    "keywords": [
        "NASA",
        "MODIS",
        "Satellite",
        "Imagery",
        "Global",
        "Fire",
        "MCD64A1"
    ],
    "providers": [
        {
            "name": "NASA LP DAAC at the USGS EROS Center",
            "roles": [
                "producer",
                "licensor",
                "processor"
            ],
            "url": "https://lpdaac.usgs.gov/"
        },
        {
            "name": "Microsoft",
            "roles": [
                "host",
                "processor"
            ],
            "url": "https://planetarycomputer.microsoft.com"
        }
    ],
    "summaries": {
        "platform": [
            "aqua",
            "terra"
        ],
        "instruments": [
            "modis"
        ]
    },
    "assets": {
        "thumbnail": {
            "href": "https://ai4edatasetspublicassets.blob.core.windows.net/assets/pc_thumbnails/modis-64A1-061.png",
            "type": "image/png",
            "title": "MODIS Burned Area Monthly thumbnail",
            "roles": [
                "thumbnail"
            ]
        },
        "geoparquet-items": {
            "href": "abfs://items/modis-64A1-061.parquet",
            "type": "application/x-parquet",
            "title": "GeoParquet STAC items",
            "description": "Snapshot of the collection's STAC items exported to GeoParquet format.",
            "msft:partition_info": {
                "is_partitioned": true,
                "partition_frequency": "MS"
            },
            "table:storage_options": {
                "account_name": "pcstacitems"
            },
            "roles": [
                "stac-items"
            ]
        }
    }
}